gamestart/__init__.py
gamestart/actor.py
gamestart/fill.py
gamestart/game.py
gamestart/shapes.py
gamestart/sound.py
gamestart/text.py
gamestart/vendor/__init__.py
gamestart/vendor/ptext.py
gamestart-0.0.1.dist-info/LICENSE
gamestart-0.0.1.dist-info/METADATA
gamestart-0.0.1.dist-info/WHEEL
gamestart-0.0.1.dist-info/top_level.txt
gamestart-0.0.1.dist-info/RECORD
