Metadata-Version: 2.1
Name: gamestart
Version: 0.0.1
Summary: Pygame wrapper for learners, jammers and educators
Home-page: https://github.com/bigeyex/python-adminui
Author: Yu Wang (bigeyex)
Author-email: bigeyex@gmail.com
License: UNKNOWN
Platform: UNKNOWN
Classifier: Programming Language :: Python :: 3
Classifier: License :: OSI Approved :: MIT License
Classifier: Operating System :: OS Independent
Requires-Python: >=3.6
Requires-Dist: pygame
